pixpdv/__init__.py
pixpdv/pixpdv.py
PIXPDV-1.0.2.dist-info/LICENSE
PIXPDV-1.0.2.dist-info/METADATA
PIXPDV-1.0.2.dist-info/WHEEL
PIXPDV-1.0.2.dist-info/top_level.txt
PIXPDV-1.0.2.dist-info/RECORD
