Metadata-Version: 2.1
Name: PIXPDV
Version: 1.0.2
Summary: Uma biblioteca para interagir com o serviço PIXPDV.
Home-page: https://github.com/PIXPDV/python
Author: PIXPDV
Author-email: sac@pixpdv.com.br
Classifier: License :: OSI Approved :: MIT License
Classifier: Programming Language :: Python :: 3
Classifier: Programming Language :: Python :: 3.6
Classifier: Programming Language :: Python :: 3.7
Classifier: Programming Language :: Python :: 3.8
Classifier: Programming Language :: Python :: 3.9
License-File: LICENSE
Requires-Dist: requests
